joeynmt/__init__.py
joeynmt/__main__.py
joeynmt/attention.py
joeynmt/batch.py
joeynmt/builders.py
joeynmt/config.py
joeynmt/data.py
joeynmt/datasets.py
joeynmt/decoders.py
joeynmt/embeddings.py
joeynmt/encoders.py
joeynmt/helpers.py
joeynmt/helpers_for_ddp.py
joeynmt/hub_interface.py
joeynmt/initialization.py
joeynmt/loss.py
joeynmt/metrics.py
joeynmt/model.py
joeynmt/plotting.py
joeynmt/prediction.py
joeynmt/search.py
joeynmt/tokenizers.py
joeynmt/training.py
joeynmt/transformer_layers.py
joeynmt/vocabulary.py
test/__init__.py
test/unit/__init__.py
test/unit/test_attention.py
test/unit/test_batch.py
test/unit/test_data.py
test/unit/test_dataset.py
test/unit/test_decoder.py
test/unit/test_embeddings.py
test/unit/test_encoder.py
test/unit/test_loss.py
test/unit/test_metric.py
test/unit/test_model_init.py
test/unit/test_prediction.py
test/unit/test_search.py
test/unit/test_tokenizer.py
test/unit/test_transformer_decoder.py
test/unit/test_transformer_encoder.py
test/unit/test_transformer_utils.py
test/unit/test_vocabulary.py
test/unit/test_weight_tying.py
joeynmt-2.3.0.dist-info/LICENSE
joeynmt-2.3.0.dist-info/METADATA
joeynmt-2.3.0.dist-info/WHEEL
joeynmt-2.3.0.dist-info/top_level.txt
joeynmt-2.3.0.dist-info/RECORD
