Metadata-Version: 2.1
Name: joeynmt
Version: 2.3.0
Summary: Minimalist NMT for educational purposes
Home-page: https://github.com/joeynmt/joeynmt
Author: Jasmijn Bastings and Julia Kreutzer
License: Apache License
Project-URL: Documentation, http://joeynmt.readthedocs.io/en/latest/
Project-URL: Source, https://github.com/joeynmt/joeynmt
Project-URL: Tracker, https://github.com/joeynmt/joeynmt/issues
Classifier: Intended Audience :: Developers
Classifier: Intended Audience :: Education
Classifier: Intended Audience :: Science/Research
Classifier: License :: OSI Approved :: Apache Software License
Classifier: Programming Language :: Python :: 3
Classifier: Programming Language :: Python :: 3.7
Classifier: Programming Language :: Python :: 3.8
Classifier: Programming Language :: Python :: 3.9
Classifier: Programming Language :: Python :: 3.10
Classifier: Programming Language :: Python :: 3.11
Classifier: Topic :: Scientific/Engineering :: Artificial Intelligence
Classifier: Topic :: Software Development :: Libraries :: Python Modules
Classifier: Topic :: Software Development :: Libraries
Requires-Python: >=3.7
License-File: LICENSE
Requires-Dist: future
Requires-Dist: pillow
Requires-Dist: numpy >=1.19.5
Requires-Dist: setuptools >=41.0.0
Requires-Dist: torch >=1.12.0
Requires-Dist: protobuf <3.21,>=3.19.4
Requires-Dist: tensorboard >=1.15
Requires-Dist: sacrebleu >=2.0.0
Requires-Dist: sacremoses
Requires-Dist: sentencepiece
Requires-Dist: subword-nmt
Requires-Dist: matplotlib
Requires-Dist: seaborn
Requires-Dist: pyyaml >=5.1
Requires-Dist: six >=1.12
Requires-Dist: wrapt >=1.11.1
Requires-Dist: pylint
Requires-Dist: yapf
Requires-Dist: flake8
Requires-Dist: pytest
Requires-Dist: datasets
Requires-Dist: packaging
Requires-Dist: plotly
Requires-Dist: pandas
